db_check/__init__.py
db_check/__main__.py
db_check/checklist.py
db_check/clustering.py
db_check/messages.py
db_check/parsers.py
db_check/report.py
db_check/examples/example_db.fasta
db_check/examples/example_db_pipe.fasta
tests/__init__.py
tests/test_parsers.py
db_check-0.1.5.dist-info/METADATA
db_check-0.1.5.dist-info/WHEEL
db_check-0.1.5.dist-info/entry_points.txt
db_check-0.1.5.dist-info/top_level.txt
db_check-0.1.5.dist-info/RECORD
