Metadata-Version: 2.1
Name: db-check
Version: 0.1.5
Summary: Sanity check your FASTA DB before release.
Home-page: https://github.com/andersgs/db_check
Author: Anders Gonçalves da Silva
Author-email: andersgs@gmail.com
License: UNKNOWN
Platform: UNKNOWN
Classifier: License :: OSI Approved :: GNU Lesser General Public License v3 (LGPLv3)
Classifier: Programming Language :: Python :: 3
Classifier: Programming Language :: Python :: 3.6
Classifier: Programming Language :: Python :: 3.7
Requires-Dist: click
Requires-Dist: pandas
Requires-Dist: sh
Requires-Dist: tabulate (>=0.8.2)
Requires-Dist: markdown-strings
